{"2PBJWahiIRAiT/fRoP0pzg==":"mt-0548-home-logo-77x75.png","iNsvrkOI17b4bnwiN2Hbcg==":"exterior-1024x683.png","t2lG5xlJ591dK/a2ssDEdw==":"interior.tn-1200x627.png","CSJilDaxBT4m4IztmS/2vw==":"untitled-315x160.png","hQ9I6LaZoOtq+Sw4j+2m8g==":"worship-259x194.png","Eyh3UTwQDMs3aNoB6QM4eA==":"ch-274x184.png","3ASgnSMxiQrnMHDNKm7L6w==":"mt-0548-home-image1111-596x446.png","UskxGR3SiYXA3WWE7ldYHw==":"thumb-1920-1920x1200.png","bxE4mWccrkpz7cdjMYzT6w==":"unnamedqn5d0t61-512x288.png","G8FhQNfl6DkA3WlqqQXQng==":"3-church-1600x1198.png","2EOxpjDdg1p1BFtuQQFU9w==":"background3.jpeg","25NWAJgHJOmxLK4n/tqBlQ==":"ministries-img1-3-255x255.png","Siy3lkzeQOq80hIdecK8Vw==":"ministries-img1-4-255x255.png","mAg7zR79632YWJaih7Vkuw==":"ministries-img1-5-255x255.png"}